nhpy/__init__.py
nhpy/__meta__.py
nhpy/__vars__.py
nhpy/api_paths.py
nhpy/errors.py
nhpy/nbook.py
nhpy/ncomment.py
nhpy/npages.py
nhpy/ntag.py
nhpy/nuser.py
nhpy/test.py
nhpy/wrapper.py
nhpy-0.1.3.dist-info/LICENSE
nhpy-0.1.3.dist-info/METADATA
nhpy-0.1.3.dist-info/WHEEL
nhpy-0.1.3.dist-info/top_level.txt
nhpy-0.1.3.dist-info/RECORD
