Metadata-Version: 2.1
Name: nhpy
Version: 0.1.3
Summary: API wraper for nhentai.net
Home-page: https://github.com/b3yc0d3/nhpy
Author: b3yc0d3
Author-email: b3yc0d3@dnmx.org
License: UNKNOWN
Project-URL: Source, https://github.com/b3yc0d3/nhpy
Project-URL: Issue tracker, https://github.com/b3yc0d3/nhpy/issues
Platform: UNKNOWN
Classifier: Development Status :: 1 - Planning
Classifier: Programming Language :: Python :: 3.7
Classifier: Programming Language :: Python :: 3.8
Classifier: Programming Language :: Python :: 3.9
Classifier: Programming Language :: Python :: 3.10
Classifier: License :: OSI Approved :: GNU General Public License v3 (GPLv3)
Classifier: Operating System :: OS Independent
License-File: LICENSE
Requires-Dist: requests (>=2.27.1)
